{
  "boris.glb": "primary_000.glb",
  "boris_glasses.glb": "secondary_000.glb",
  "guard.glb": "primary_001.glb",
  "guard_1.glb": "primary_002.glb",
  "guard_2.glb": "primary_017.glb",
  "blue_chair.glb": "secondary_022.glb",
  "metal_crate.glb": "primary_023.glb",
  "wooden_table.glb": "primary_024.glb",
  "wooden_crate.glb": "primary_025.glb",
  "metal_crate_1.glb": "primary_026.glb",
  "cardboard_crate.glb": "primary_027.glb",
  "wooden_crate_1.glb": "primary_029.glb",
  "body_armor.glb": "primary_031.glb",
  "cardboard_crate_1.glb": "primary_035.glb",
  "metal_table_primary.glb": "primary_036.glb",
  "metal_table_secondary.glb": "secondary_036.glb",
  "body_armor_1.glb": "primary_039.glb",
  "ammo_crate.glb": "primary_041.glb",
  "mainframe.glb": "primary_042.glb",
  "mainframe_1.glb": "primary_043.glb",
  "monitor_holder_primary.glb": "primary_044.glb",
  "monitor_holder_secondary.glb": "secondary_044.glb",
  "tv.glb": "primary_047.glb",
  "keyboard.glb": "primary_048.glb",
  "encryption_key_primary.glb": "primary_049.glb",
  "encryption_key_secondary.glb": "secondary_049.glb",
  "glass_door_primary.glb": "primary_052.glb",
  "glass_door_secondary.glb": "secondary_052.glb",
  "glass_door_primary_1.glb": "primary_053.glb",
  "glass_door_secondary_1.glb": "secondary_053.glb",
  "brown_sliding_door.glb": "primary_058.glb",
  "metal_door_primary.glb": "primary_059.glb",
  "metal_door_secondary.glb": "secondary_059.glb",
  "metal_door_primary_1.glb": "primary_060.glb",
  "metal_door_secondary_1.glb": "secondary_060.glb",
  "metal_door.glb": "primary_067.glb",
  "security_camera_primary.glb": "primary_069.glb",
  "security_camera_secondary.glb": "secondary_069.glb",
  "alarm.glb": "primary_073.glb",
  "divider.glb": "primary_075.glb",
  "divider_1.glb": "primary_078.glb",
  "divider_2.glb": "primary_081.glb",
  "divider_3.glb": "primary_085.glb",
  "divider_4.glb": "primary_086.glb",
  "divider_5.glb": "primary_095.glb",
  "console.glb": "primary_096.glb",
  "console_1.glb": "primary_097.glb",
  "console_2.glb": "primary_098.glb",
  "console_3.glb": "primary_099.glb",
  "window_glass.glb": "secondary_101.glb"
}